lintception/Utils.py
lintception/__init__.py
lintception/linters.py
lintception/main.py
lintception/my_linter.py
lintception-1.0.2.dist-info/LICENSE
lintception-1.0.2.dist-info/METADATA
lintception-1.0.2.dist-info/WHEEL
lintception-1.0.2.dist-info/entry_points.txt
lintception-1.0.2.dist-info/top_level.txt
lintception-1.0.2.dist-info/RECORD
